spoofbot/__init__.py
spoofbot/browser.py
spoofbot/operating_system.py
spoofbot/scheduler.py
spoofbot/tag.py
spoofbot/adapter/__init__.py
spoofbot/adapter/cache.py
spoofbot/adapter/file.py
spoofbot/adapter/har.py
spoofbot/adapter/mitmproxy.py
spoofbot/replay/__init__.py
spoofbot/replay/replay.py
spoofbot/util/__init__.py
spoofbot/util/archive.py
spoofbot/util/common.py
spoofbot/util/file.py
spoofbot/util/har.py
spoofbot/util/http.py
spoofbot/util/log.py
spoofbot/util/versions.py
spoofbot-1.4.0.dist-info/LICENSE
spoofbot-1.4.0.dist-info/METADATA
spoofbot-1.4.0.dist-info/WHEEL
spoofbot-1.4.0.dist-info/top_level.txt
spoofbot-1.4.0.dist-info/RECORD
