Metadata-Version: 2.1
Name: spoofbot
Version: 1.4.0
Summary: Web bot for spoofing browser behaviour when using python requests
Home-page: https://pypi.org/project/spoofbot/
Author: raember
Author-email: raember <raember@users.noreply.github.com>
License: MIT License
Project-URL: Home, https://pypi.org/project/spoofbot/
Classifier: License :: OSI Approved :: MIT License
Requires-Python: >=3.10
License-File: LICENSE
Requires-Dist: requests
Requires-Dist: urllib3
Requires-Dist: bs4
Requires-Dist: pillow
Requires-Dist: toposort
Requires-Dist: brotli
Requires-Dist: publicsuffix2
Requires-Dist: loguru
Requires-Dist: python-dateutil
Requires-Dist: aiohttp
Requires-Dist: pyopenssl
Provides-Extra: dev
Requires-Dist: docker; extra == "dev"
Provides-Extra: mitmproxy
Requires-Dist: mitmproxy~=7.0.4; extra == "mitmproxy"
